unleashed_chat_cli/__init__.py
unleashed_chat_cli/main.py
unleashed_chat_cli-0.1.0.dist-info/METADATA
unleashed_chat_cli-0.1.0.dist-info/WHEEL
unleashed_chat_cli-0.1.0.dist-info/entry_points.txt
unleashed_chat_cli-0.1.0.dist-info/top_level.txt
unleashed_chat_cli-0.1.0.dist-info/RECORD
