Metadata-Version: 2.1
Name: unleashed-chat-cli
Version: 0.1.0
Summary: A simple CLI wrapper for Unleashed.chat's chatbot service.
Home-page: https://github.com/reecehunter/unleashed-chat-cli
Author: Reece Hunter
Classifier: Programming Language :: Python :: 3
Classifier: License :: OSI Approved :: MIT License
Classifier: Operating System :: OS Independent
Requires-Python: >=3.6
Requires-Dist: openai
Requires-Dist: python-dotenv
